optitrader/__init__.py
optitrader/api.py
optitrader/app/1_🏠_Home.py
optitrader/app/__init__.py
optitrader/app/about.py
optitrader/app/account.py
optitrader/app/backtester.py
optitrader/app/explore.py
optitrader/app/home.py
optitrader/app/page.py
optitrader/app/pages/2_📈_Backtester.py
optitrader/app/pages/3_🗺️_Explore.py
optitrader/app/pages/4_💼_Account.py
optitrader/app/pages/5_👨🏻‍💻_About.py
optitrader/app/pages/__init__.py
optitrader/app/session_manager.py
optitrader/backtester.py
optitrader/cli.py
optitrader/config.py
optitrader/enums/__init__.py
optitrader/enums/backtester.py
optitrader/enums/iterable.py
optitrader/enums/market.py
optitrader/enums/optimization.py
optitrader/main.py
optitrader/market/__init__.py
optitrader/market/alpaca_market_data.py
optitrader/market/base_data_provider.py
optitrader/market/db/__init__.py
optitrader/market/db/database.py
optitrader/market/db/models.py
optitrader/market/db/scripts/__init__.py
optitrader/market/db/scripts/add_asset.py
optitrader/market/db/scripts/create_assets_table.py
optitrader/market/db/scripts/update_number_of_shares.py
optitrader/market/finnhub_market_data.py
optitrader/market/investment_universe.py
optitrader/market/market_data.py
optitrader/market/trading.py
optitrader/market/yahoo_market_data.py
optitrader/models/__init__.py
optitrader/models/asset.py
optitrader/models/base.py
optitrader/models/optimization.py
optitrader/optimization/__init__.py
optitrader/optimization/constraints.py
optitrader/optimization/objectives.py
optitrader/optimization/solver.py
optitrader/portfolio.py
optitrader/py.typed
optitrader/utils/__init__.py
optitrader/utils/utils.py
optitrader-0.2.2.dist-info/LICENSE
optitrader-0.2.2.dist-info/METADATA
optitrader-0.2.2.dist-info/WHEEL
optitrader-0.2.2.dist-info/entry_points.txt
optitrader-0.2.2.dist-info/RECORD
