Metadata-Version: 2.3
Name: optitrader
Version: 0.2.2
Summary: Optitrader is an open-source Python package for portfolio optimization and algorithmic trading. 
Author: Alessio Castrica
Author-email: castricaalessio@gmail.com
Requires-Python: >=3.10,<4.0
Classifier: Programming Language :: Python :: 3
Classifier: Programming Language :: Python :: 3.10
Classifier: Programming Language :: Python :: 3.11
Classifier: Programming Language :: Python :: 3.12
Classifier: Programming Language :: Python :: 3.13
Requires-Dist: alpaca-py (>=0.13.4,<0.14.0)
Requires-Dist: certifi (>=2023.11.17,<2024.0.0)
Requires-Dist: coloredlogs (>=15.0.1)
Requires-Dist: cvxpy (>=1.6.4)
Requires-Dist: fastapi[all] (>=0.92.0)
Requires-Dist: finnhub-python (>=2.4.18,<3.0.0)
Requires-Dist: gunicorn (>=20.1.0)
Requires-Dist: html5lib (>=1.1,<2.0)
Requires-Dist: jupyter-server (>=2.12.1,<3.0.0)
Requires-Dist: lxml (==4.9.2)
Requires-Dist: matplotlib (>=3.7.1,<4.0.0)
Requires-Dist: nbconvert (>=7.12.0,<8.0.0)
Requires-Dist: nbformat (>=5.9.2,<6.0.0)
Requires-Dist: pandas (>=2.2.3)
Requires-Dist: plotly (>=5.15.0)
Requires-Dist: poethepoet (>=0.20.0)
Requires-Dist: protobuf (>=4.25.1,<5.0.0)
Requires-Dist: pydantic (>=2.5.2)
Requires-Dist: requests (>=2.32.3)
Requires-Dist: scipy (>=1.11.4,<2.0.0)
Requires-Dist: sqlalchemy (>=2.0.19,<3.0.0)
Requires-Dist: streamlit (>=1.43.2)
Requires-Dist: typeguard (>=4.0.0,<5.0.0)
Requires-Dist: typer[all] (>=0.9.0)
Requires-Dist: urllib3 (>=2.1.0,<3.0.0)
Requires-Dist: uvicorn[standard] (>=0.20.0)
Requires-Dist: watchdog (>=3.0.0,<4.0.0)
Requires-Dist: yahooquery (>=2.3.1,<3.0.0)
Project-URL: Repository, https://github.com/Ale-Cas/optitrader
